perceptra_seg/__init__.py
perceptra_seg/__version__.py
perceptra_seg/cli.py
perceptra_seg/config.py
perceptra_seg/core.py
perceptra_seg/exceptions.py
perceptra_seg/models.py
perceptra_seg/py.typed
perceptra_seg/quickstart.py
perceptra_seg/backends/__init__.py
perceptra_seg/backends/base.py
perceptra_seg/backends/onnx_sam_v1.py
perceptra_seg/backends/onnx_sam_v2.py
perceptra_seg/backends/torch_sam_v1.py
perceptra_seg/backends/torch_sam_v2.py
perceptra_seg/utils/__init__.py
perceptra_seg/utils/cache.py
perceptra_seg/utils/dependency_check.py
perceptra_seg/utils/image_io.py
perceptra_seg/utils/mask_utils.py
perceptra_seg/utils/tiling.py
perceptra_seg-0.1.1.dist-info/licenses/LICENSE
service/__init__.py
service/main.py
service/middleware.py
service/routes.py
perceptra_seg-0.1.1.dist-info/METADATA
perceptra_seg-0.1.1.dist-info/WHEEL
perceptra_seg-0.1.1.dist-info/entry_points.txt
perceptra_seg-0.1.1.dist-info/top_level.txt
perceptra_seg-0.1.1.dist-info/RECORD
