Metadata-Version: 2.4
Name: perceptra-seg
Version: 0.1.1
Summary: Production-grade segmentation tool with SAM v1/v2 support
Author-email: Segmentor Team <team@example.com>
License: Apache-2.0
Project-URL: Homepage, https://github.com/tannousgeagea/perceptra-seg
Project-URL: Documentation, https://perceptra-seg.readthedocs.io
Project-URL: Repository, https://github.com/tannousgeagea/perceptra-seg
Keywords: segmentation,sam,computer-vision,deep-learning
Classifier: Development Status :: 4 - Beta
Classifier: Intended Audience :: Developers
Classifier: License :: OSI Approved :: Apache Software License
Classifier: Programming Language :: Python :: 3.10
Classifier: Programming Language :: Python :: 3.11
Classifier: Programming Language :: Python :: 3.12
Requires-Python: >=3.10
License-File: LICENSE
Requires-Dist: numpy>=1.24.0
Requires-Dist: pillow>=10.0.0
Requires-Dist: shapely>=2.0.0
Requires-Dist: opencv-python>=4.8.0
Requires-Dist: pydantic>=2.0.0
Requires-Dist: pyyaml>=6.0
Requires-Dist: requests>=2.31.0
Requires-Dist: typing-extensions>=4.8.0
Provides-Extra: torch
Requires-Dist: torch>=2.0.0; extra == "torch"
Requires-Dist: torchvision>=0.15.0; extra == "torch"
Provides-Extra: onnx
Requires-Dist: onnxruntime>=1.16.0; extra == "onnx"
Requires-Dist: onnxruntime-gpu>=1.16.0; extra == "onnx"
Provides-Extra: server
Requires-Dist: fastapi>=0.104.0; extra == "server"
Requires-Dist: uvicorn[standard]>=0.24.0; extra == "server"
Requires-Dist: python-multipart>=0.0.6; extra == "server"
Requires-Dist: prometheus-client>=0.19.0; extra == "server"
Provides-Extra: dev
Requires-Dist: pytest>=7.4.0; extra == "dev"
Requires-Dist: pytest-cov>=4.1.0; extra == "dev"
Requires-Dist: pytest-asyncio>=0.21.0; extra == "dev"
Requires-Dist: black>=23.11.0; extra == "dev"
Requires-Dist: isort>=5.12.0; extra == "dev"
Requires-Dist: ruff>=0.1.5; extra == "dev"
Requires-Dist: mypy>=1.7.0; extra == "dev"
Requires-Dist: pre-commit>=3.5.0; extra == "dev"
Requires-Dist: httpx>=0.25.0; extra == "dev"
Provides-Extra: docs
Requires-Dist: mkdocs>=1.5.0; extra == "docs"
Requires-Dist: mkdocs-material>=9.4.0; extra == "docs"
Provides-Extra: all
Requires-Dist: perceptra-seg[dev,docs,onnx,server,torch]; extra == "all"
Dynamic: license-file
